LICENSE
README.md
setup.py
p2k/__init__.py
p2k/proxy.py
p2k/utils.py
p2k/visual.py
p2k.egg-info/PKG-INFO
p2k.egg-info/SOURCES.txt
p2k.egg-info/dependency_links.txt
p2k.egg-info/not-zip-safe
p2k.egg-info/requires.txt
p2k.egg-info/top_level.txt